ics/__init__.py
ics/apps/__init__.py
ics/apps/web_admin.py
ics/apps/web_app.py
ics/apps/web_public.py
ics/apps/media/css/style.css
ics/apps/media/js/utility.js
ics/apps/media/template/about.html
ics/apps/media/template/admin_basewithmenu.html
ics/apps/media/template/base.html
ics/apps/media/template/basewithmenu.html
ics/apps/media/template/browseandcode.html
ics/apps/media/template/classification_view.html
ics/apps/media/template/classifiers.html
ics/apps/media/template/classify.html
ics/apps/media/template/datasets.html
ics/apps/media/template/ips.html
ics/apps/media/template/jobs.html
ics/apps/media/template/keys.html
ics/apps/media/template/locks.html
ics/apps/media/template/login.html
ics/apps/media/template/public_api.html
ics/apps/media/template/public_basewithmenu.html
ics/apps/media/template/public_typeandcode.html
ics/apps/media/template/training_data_view.html
ics/apps/media/template/typeandcode.html
ics/apps/media/template/users.html
ics/classifier/__init__.py
ics/classifier/analyzer.py
ics/classifier/classifier.py
ics/classifier/lri.py
ics/classifier/lri_online_classifier.py
ics/client/__init__.py
ics/client/client_session.py
ics/db/__init__.py
ics/db/sqlalchemydb.py
ics/scripts/__init__.py
ics/scripts/cli.py
ics/scripts/list_exposed_methods.py
ics/scripts/twitter_uploader.py
ics/scripts/webapp.py
ics/services/__init__.py
ics/services/auth_controller_service.py
ics/services/background_processor_service.py
ics/services/classifier_collection_service.py
ics/services/dataset_collection_service.py
ics/services/ip_controller_service.py
ics/services/jobs_service.py
ics/services/key_controller_service.py
ics/services/user_controller_service.py
ics/util/__init__.py
ics/util/util.py
ics_pkg-0.2.3.dist-info/COPYING
ics_pkg-0.2.3.dist-info/METADATA
ics_pkg-0.2.3.dist-info/WHEEL
ics_pkg-0.2.3.dist-info/entry_points.txt
ics_pkg-0.2.3.dist-info/top_level.txt
ics_pkg-0.2.3.dist-info/RECORD
