Metadata-Version: 2.1
Name: ics-pkg
Version: 0.2.3
Summary: Interactive Classification System (ICS): a tool for machine learning-supported labeling of text
Home-page: https://github.com/aesuli/ics
Author: Andrea Esuli
Author-email: andrea@esuli.it
License: BSD-3-Clause
Project-URL: Bug Reports, https://github.com/aesuli/ics/issues
Project-URL: Source, https://github.com/aesuli/ics/
Keywords: text,classification,labeling,machine learning,active learning
Classifier: Development Status :: 4 - Beta
Classifier: Intended Audience :: Developers
Classifier: Intended Audience :: Science/Research
Classifier: Programming Language :: Python
Classifier: Topic :: Software Development
Classifier: Topic :: Scientific/Engineering
Classifier: Programming Language :: Python :: 3
Classifier: Programming Language :: Python :: 3.8
Classifier: Programming Language :: Python :: 3.9
Classifier: Programming Language :: Python :: 3.10
Classifier: Programming Language :: Python :: 3.11
Classifier: Programming Language :: Python :: 3.12
Requires-Python: >=3.8
License-File: COPYING
Requires-Dist: CherryPy >=18.8.0
Requires-Dist: ConfigArgParse >=1.5.3
Requires-Dist: Mako >=1.2.4
Requires-Dist: SQLAlchemy >=2.0.0
Requires-Dist: numpy >=1.24.1
Requires-Dist: passlib >=1.7.4
Requires-Dist: requests >=2.28.2
Requires-Dist: scikit-learn >=1.2.1
Requires-Dist: scipy >=1.10.0
Requires-Dist: twiget >=0.1.5
